fa2/__init__.py
fa2/fa2util.c
fa2/fa2util.cp37-win_amd64.pyd
fa2/fa2util.pxd
fa2/fa2util.py
fa2/forceatlas2.py
fa2-0.3.5.dist-info/LICENSE
fa2-0.3.5.dist-info/METADATA
fa2-0.3.5.dist-info/WHEEL
fa2-0.3.5.dist-info/top_level.txt
fa2-0.3.5.dist-info/RECORD
